<?xml version="1.0" encoding="UTF-8"?>
<LAWXML>
	<Translate language="ptbr" version="10.0">
		<phrase id="CM_0"><![CDATA[Para exibir]]></phrase>
		<phrase id="CM_1"><![CDATA[detalhes de formação, certificação e competência,]]></phrase>
		<phrase id="CM_2"><![CDATA[clique no link de qualificação no gráfico.]]></phrase>
		<phrase id="CM_3"><![CDATA[Nível de proficiência]]></phrase>
		<phrase id="CM_4"><![CDATA[Funcionário]]></phrase>
		<phrase id="CM_5"><![CDATA[Emprego]]></phrase>
		<phrase id="CM_6"><![CDATA[Nenhum nível de proficiência]]></phrase>
		<phrase id="CM_7"><![CDATA[Não há qualificações definidas]]></phrase>
		<phrase id="CM_8"><![CDATA[para você ou seu emprego no momento.]]></phrase>
		<phrase id="CM_9"><![CDATA[para seu emprego.]]></phrase>
		<phrase id="CM_10"><![CDATA[Somente suas qualificações serão exibidas.]]></phrase>
		<phrase id="CM_11"><![CDATA[Não há detalhes para exibir]]></phrase>
		<phrase id="CM_12"><![CDATA[para essa qualificação.]]></phrase>
		<phrase id="CM_13"><![CDATA[Não há qualificações listadas para você.]]></phrase>
		<phrase id="CM_14"><![CDATA[As qualificações serão exibidas]]></phrase>
		<phrase id="CM_15"><![CDATA[definidas somente para o emprego.]]></phrase>
		<phrase id="CM_16"><![CDATA[Selecione um relatório direto]]></phrase>
		<phrase id="CM_17"><![CDATA[para comparar suas qualificações]]></phrase>
		<phrase id="CM_18"><![CDATA[com as definidas para seu emprego.]]></phrase>
		<phrase id="CM_19"><![CDATA[Selecione um emprego abaixo]]></phrase>
		<phrase id="CM_20"><![CDATA[para comparar suas qualificações]]></phrase>
		<phrase id="CM_21"><![CDATA[com as definidas para o emprego.]]></phrase>
		<phrase id="CM_22"><![CDATA[Selecione um emprego.]]></phrase>
		<phrase id="CM_23"><![CDATA[Cargo]]></phrase>
		<phrase id="CM_24"><![CDATA[Selecione um funcionário.]]></phrase>
		<phrase id="CM_25"><![CDATA[Para criar um perfil,]]></phrase>
		<phrase id="CM_26"><![CDATA[é preciso selecionar um cargo e um funcionário.]]></phrase>
		<phrase id="CM_27"><![CDATA[Selecione um emprego e um funcionário]]></phrase>
		<phrase id="CM_28"><![CDATA[Categoria do emprego]]></phrase>
		<phrase id="CM_29"><![CDATA[Selecione uma categoria abaixo]]></phrase>
		<phrase id="CM_30"><![CDATA[para criar uma lista de empregos.]]></phrase>
		<phrase id="CM_31"><![CDATA[Então,]]></phrase>
		<phrase id="CM_32"><![CDATA[será possível selecionar um emprego]]></phrase>
		<phrase id="CM_33"><![CDATA[e comparar suas qualificações]]></phrase>
		<phrase id="CM_34"><![CDATA[Primeiro, é preciso selecionar uma categoria de emprego.]]></phrase>
		<phrase id="CM_35"><![CDATA[Atualmente não há empregos]]></phrase>
		<phrase id="CM_36"><![CDATA[associados com esta categoria.]]></phrase>
		<phrase id="CM_37"><![CDATA[você selecionará um funcionário e um emprego]]></phrase>
		<phrase id="CM_38"><![CDATA[Selecione um funcionário e um emprego abaixo]]></phrase>
		<phrase id="CM_39"><![CDATA[para criar um perfil.]]></phrase>
		<phrase id="CM_40"><![CDATA[Para encontrar outros empregos]]></phrase>
		<phrase id="CM_41"><![CDATA[que correspondem com suas qualificações,]]></phrase>
		<phrase id="CM_42"><![CDATA[clique em "Criar lista de empregos" abaixo.]]></phrase>
		<phrase id="CM_43"><![CDATA[Se quiser adicionar]]></phrase>
		<phrase id="CM_44"><![CDATA[outras áreas de interesse na pesquisa de empregos,]]></phrase>
		<phrase id="CM_45"><![CDATA[é possível selecioná-las abaixo.]]></phrase>
		<phrase id="CM_46"><![CDATA[Qualificação]]></phrase>
		<phrase id="CM_47"><![CDATA[Certificação]]></phrase>
		<phrase id="CM_48"><![CDATA[Competência]]></phrase>
		<phrase id="CM_49"><![CDATA[Formação]]></phrase>
		<phrase id="CM_50"><![CDATA[Tipo]]></phrase>
		<phrase id="CM_51"><![CDATA[definido para os critérios informados]]></phrase>
		<phrase id="CM_52"><![CDATA[(de acordo com todos os requisitos do emprego]]></phrase>
		<phrase id="CM_53"><![CDATA[ou somente os requisitos essenciais).]]></phrase>
		<phrase id="CM_54"><![CDATA[Os empregos listados abaixo baseiam-se em]]></phrase>
		<phrase id="CM_55"><![CDATA[requisitos essenciais e]]></phrase>
		<phrase id="CM_56"><![CDATA[não essenciais do emprego.]]></phrase>
		<phrase id="CM_57"><![CDATA[Não há empregos definidos]]></phrase>
		<phrase id="CM_58"><![CDATA[de acordo com todos os requisitos do emprego.]]></phrase>
		<phrase id="CM_59"><![CDATA[Os empregos mostrados abaixo baseiam-se]]></phrase>
		<phrase id="CM_60"><![CDATA[somente em requisitos essenciais.]]></phrase>
		<phrase id="CM_61"><![CDATA[que correspondem às qualificações do funcionário,]]></phrase>
		<phrase id="CM_62"><![CDATA[selecione um funcionário, depois]]></phrase>
		<phrase id="CM_63"><![CDATA[Primeiro é preciso selecionar um funcionário.]]></phrase>
		<phrase id="CM_64"><![CDATA[Selecione uma qualificação abaixo para pesquisar por]]></phrase>
		<phrase id="CM_65"><![CDATA[cursos oferecidos pela empresa.]]></phrase>
		<phrase id="CM_66"><![CDATA[Se várias qualificações forem selecionadas,]]></phrase>
		<phrase id="CM_67"><![CDATA[o sistema irá pesquisar por todos os cursos que]]></phrase>
		<phrase id="CM_68"><![CDATA[abordam as qualificações selecionadas.]]></phrase>
		<phrase id="CM_69"><![CDATA[Competências]]></phrase>
		<phrase id="CM_70"><![CDATA[Certificações]]></phrase>
		<phrase id="CM_71"><![CDATA[Selecione um emprego abaixo.]]></phrase>
		<phrase id="CM_72"><![CDATA[Um perfil será criado.]]></phrase>
		<phrase id="CM_73"><![CDATA[Clique em uma qualificação no perfil]]></phrase>
		<phrase id="CM_74"><![CDATA[para visualizar quais cursos estão disponíveis.]]></phrase>
		<phrase id="CM_75"><![CDATA[Selecione um funcionário e um emprego abaixo.]]></phrase>
		<phrase id="CM_76"><![CDATA[meu emprego atual]]></phrase>
		<phrase id="CM_77"><![CDATA[Anexo do plano de ação]]></phrase>
		<phrase id="CM_78"><![CDATA[Bem-vindo ao seu Centro de gestão de carreiras]]></phrase>
		<phrase id="CM_79"><![CDATA[Essas qualificações venceram ou vencerão dentro de]]></phrase>
		<phrase id="CM_80"><![CDATA[dias.]]></phrase>
		<phrase id="CM_81"><![CDATA[Você não qualificações a vencer nos próximos]]></phrase>
		<phrase id="CM_82"><![CDATA[Um emprego que você marcou está aberto. Clique no link abaixo para obter mais informações.]]></phrase>
		<phrase id="CM_83"><![CDATA[Não há vagas para os empregos nos quais você está interessado.]]></phrase>
		<phrase id="CM_84"><![CDATA[Podemos monitorar quando empregos nos quais você está interessado ficarão disponíveis. Para configurar os empregos que deseja monitorar, clique em]]></phrase>
		<phrase id="CM_85"><![CDATA[Vagas de emprego]]></phrase>
		<phrase id="CM_86"><![CDATA[Nenhuma especificada.]]></phrase>
		<phrase id="CM_87"><![CDATA[Atualização concluída!]]></phrase>
		<phrase id="CM_88"><![CDATA[Excluir seu plano de ação?]]></phrase>
		<phrase id="CM_89"><![CDATA[Meu plano de ação]]></phrase>
		<phrase id="CM_90"><![CDATA[Imprimir]]></phrase>
		<phrase id="CM_91"><![CDATA[Excluir]]></phrase>
		<phrase id="CM_92"><![CDATA[Alterar plano]]></phrase>
		<phrase id="CM_93"><![CDATA[Criar plano]]></phrase>
		<phrase id="CM_94"><![CDATA[Cancelar]]></phrase>
		<phrase id="CM_95"><![CDATA[Atualizar]]></phrase>
		<phrase id="CM_96"><![CDATA[Imprimir plano de ação]]></phrase>
		<phrase id="CM_97"><![CDATA[Excluir plano de ação]]></phrase>
		<phrase id="CM_98"><![CDATA[Alterar plano de ação]]></phrase>
		<phrase id="CM_99"><![CDATA[Criar plano de ação]]></phrase>
		<phrase id="CM_100"><![CDATA[Cancelar plano de ação]]></phrase>
		<phrase id="CM_101"><![CDATA[Atualizar plano de ação]]></phrase>
		<phrase id="CM_102"><![CDATA[Nome do plano de ação:]]></phrase>
		<phrase id="CM_103"><![CDATA[Alerta de qualificações]]></phrase>
		<phrase id="CM_104"><![CDATA[Alerta de emprego]]></phrase>
		<phrase id="CM_105"><![CDATA[Detalhes de qualificações]]></phrase>
		<phrase id="CM_106"><![CDATA[Aplicar alterações]]></phrase>
		<phrase id="CM_107"><![CDATA[Links relacionados]]></phrase>
		<phrase id="CM_108"><![CDATA[Próxima revisão:]]></phrase>
		<phrase id="CM_109"><![CDATA[(Não agendada)]]></phrase>
		<phrase id="CM_110"><![CDATA[Última atualização:]]></phrase>
		<phrase id="CM_111"><![CDATA[Plano de ação:]]></phrase>
		<phrase id="CM_112"><![CDATA[Se desejar criar um Plano de ação para definir objetivos de carreira, identificar tarefas ou projetos-chave e as datas-alvo associadas, clique no botão abaixo.]]></phrase>
		<phrase id="CM_113"><![CDATA[Essas informações estarão disponíveis para serem revisadas por que seu gerente o ajude a alcançar seus objetivos]]></phrase>
		<phrase id="CM_114"><![CDATA[Instruções]]></phrase>
		<phrase id="CM_115"><![CDATA[Explorar carreiras permite que você visualize quais empregos existem em sua empresa e comparar suas qualificações com as necessárias para o emprego.]]></phrase>
		<phrase id="CM_116"><![CDATA[Selecione um cargo abaixo para criar um perfil.]]></phrase>
		<phrase id="CM_117"><![CDATA[Criar perfil]]></phrase>
		<phrase id="CM_118"><![CDATA[Selecione uma categoria abaixo para criar uma lista de empregos.]]></phrase>
		<phrase id="CM_119"><![CDATA[Criar lista de empregos]]></phrase>
		<phrase id="CM_120"><![CDATA[Exibir perfil de qualificações atual]]></phrase>
		<phrase id="CM_121"><![CDATA[Para encontrar outros empregos que correspondem a suas qualificações, clique no botão Criar lista de empregos abaixo.<p>Se desejar adicionar outras áreas de interesse a sua pesquisa de empregos por qualificação, é possível selecioná-las abaixo.]]></phrase>
		<phrase id="CM_122"><![CDATA[Limpar qualificações]]></phrase>
		<phrase id="CM_123"><![CDATA[Criar lista de empregos]]></phrase>
		<phrase id="CM_124"><![CDATA[Selecione um emprego antes de criar um perfil.]]></phrase>
		<phrase id="CM_125"><![CDATA[Não há qualificações definidas para você ou para o emprego selecionado neste momento.]]></phrase>
		<phrase id="CM_126"><![CDATA[Não há qualificações definidas para o emprego selecionado. Somente suas qualificações serão exibidas.]]></phrase>
		<phrase id="CM_127"><![CDATA[Não há qualificações listadas para você. Somente qualificações definidas para o emprego serão exibidas.]]></phrase>
		<phrase id="CM_128"><![CDATA[Perfil do trabalho]]></phrase>
		<phrase id="CM_129"><![CDATA[Atualmente não há empregos associados a essa categoria.]]></phrase>
		<phrase id="CM_130"><![CDATA[Lista de trabalhos]]></phrase>
		<phrase id="CM_131"><![CDATA[Trabalhos aos quais se candidatou]]></phrase>
		<phrase id="CM_132"><![CDATA[Selecione até três empregos que estiver interessado.<p>Quando uma vaga abrir, iremos notificá-lo na página Meu plano de ação.]]></phrase>
		<phrase id="CM_133"><![CDATA[Aplicar]]></phrase>
		<phrase id="CM_134"><![CDATA[Descrição]]></phrase>
		<phrase id="CM_135"><![CDATA[Localização]]></phrase>
		<phrase id="CM_136"><![CDATA[Departamento]]></phrase>
		<phrase id="CM_137"><![CDATA[Enviar inscrição]]></phrase>
		<phrase id="CM_138"><![CDATA[Detalhes da vaga de emprego]]></phrase>
		<phrase id="CM_139"><![CDATA[Data de inscrição:]]></phrase>
		<phrase id="CM_140"><![CDATA[Número da requisição:]]></phrase>
		<phrase id="CM_141"><![CDATA[Nível de processo:]]></phrase>
		<phrase id="CM_142"><![CDATA[Departamento:]]></phrase>
		<phrase id="CM_143"><![CDATA[Número de vagas:]]></phrase>
		<phrase id="CM_144"><![CDATA[Supervisor:]]></phrase>
		<phrase id="CM_145"><![CDATA[Cronograma de trabalho:]]></phrase>
		<phrase id="CM_146"><![CDATA[Contato:]]></phrase>
		<phrase id="CM_147"><![CDATA[Número de telefone:]]></phrase>
		<phrase id="CM_148"><![CDATA[Ramal:]]></phrase>
		<phrase id="CM_149"><![CDATA[Selecione um emprego para atualizar.]]></phrase>
		<phrase id="CM_150"><![CDATA[Seu alerta de empregos foi atualizado.]]></phrase>
		<phrase id="CM_151"><![CDATA[Seus alertas de emprego foram atualizados.]]></phrase>
		<phrase id="CM_152"><![CDATA[Marque uma das caixas à esquerda da descrição do emprego para se candidatar para este emprego.]]></phrase>
		<phrase id="CM_153"><![CDATA[Inscrição enviada]]></phrase>
		<phrase id="CM_154"><![CDATA[Gestão de carreiras]]></phrase>
		<phrase id="CM_155"><![CDATA[Carregando Gestão de carreiras...]]></phrase>
		<phrase id="CM_156"><![CDATA[Meu perfil de trabalho]]></phrase>
		<phrase id="CM_157"><![CDATA[Minhas qualificações]]></phrase>
		<phrase id="CM_158"><![CDATA[Explorar carreiras]]></phrase>
		<phrase id="CM_159"><![CDATA[Opções de treinamento]]></phrase>
		<phrase id="CM_160"><![CDATA[Revise os objetivos de seu plano de ação. Procure por notificações de alerta sobre vagas de emprego ou qualificações vencidas.]]></phrase>
		<phrase id="CM_161"><![CDATA[Compare suas qualificações àquelas necessárias para seu emprego. Verifique onde há lacunas.]]></phrase>
		<phrase id="CM_162"><![CDATA[Visualize um resumo dos seus conhecimentos, habilidades, capacidades, certificações e educação.]]></phrase>
		<phrase id="CM_163"><![CDATA[Candidate-se a um emprego ou visualize uma lista das vagas de empregos atuais.]]></phrase>
		<phrase id="CM_164"><![CDATA[Descubra quais empregos existem em sua empresa. Pesquise por tipo ou por critérios de qualificação.]]></phrase>
		<phrase id="CM_165"><![CDATA[Encontre o treinamento que precisa por categoria, ou por critérios de definição.]]></phrase>
		<phrase id="CM_166"><![CDATA[Camada incapaz de ser escurecida]]></phrase>
		<phrase id="CM_167"><![CDATA[Camada incapaz de ser iluminada]]></phrase>
		<phrase id="CM_168"><![CDATA[No (Não)]]></phrase>
		<phrase id="CM_169"><![CDATA[Sim]]></phrase>
		<phrase id="CM_170"><![CDATA[Você não pode usar o Gestão de carreiras do gerente. Atualmente não há relatórios diretos.]]></phrase>
		<phrase id="CM_171"><![CDATA[Categoria]]></phrase>
		<phrase id="CM_172"><![CDATA[Critérios de qualificação]]></phrase>
		<phrase id="CM_173"><![CDATA[Tipo de qualificação]]></phrase>
		<phrase id="CM_174"><![CDATA[Lista de códigos de trabalho]]></phrase>
		<phrase id="CM_175"><![CDATA[Selecione um emprego e um funcionário para criar um perfil individual.]]></phrase>
		<phrase id="CM_176"><![CDATA[Selecione um emprego para criar um perfil de funcionário.]]></phrase>
		<phrase id="CM_177"><![CDATA[Selecione um emprego para criar um perfil.]]></phrase>
		<phrase id="CM_178"><![CDATA[Selecionar um trabalho.]]></phrase>
		<phrase id="CM_179"><![CDATA[Selecione um funcionário.]]></phrase>
		<phrase id="CM_180"><![CDATA[Atualmente não há empregos definidos para os critérios inseridos (baseado em todos os requisitos de emprego ou somente em requisitos essenciais).]]></phrase>
		<phrase id="CM_181"><![CDATA[Os empregos listados abaixo baseiam-se em requisitos de emprego essenciais e não essenciais.]]></phrase>
		<phrase id="CM_182"><![CDATA[Os empregos listados abaixo baseiam-se somente em requisitos de emprego essenciais. Não havia empregos definidos baseados em todos os requisitos de emprego.]]></phrase>
		<phrase id="CM_183"><![CDATA[Selecione um emprego para criar um perfil de funcionário.]]></phrase>
		<phrase id="CM_184"><![CDATA[Selecione um emprego abaixo para criar um perfil.]]></phrase>
		<phrase id="CM_185"><![CDATA[Selecionar qualificação]]></phrase>
		<phrase id="CM_186"><![CDATA[Aguarde...]]></phrase>
		<phrase id="CM_187"><![CDATA[Lista de qualificações]]></phrase>
		<phrase id="CM_188"><![CDATA[Atualmente não há qualificações definidas.]]></phrase>
		<phrase id="CM_189"><![CDATA[Valor OUT inválido]]></phrase>
		<phrase id="CM_190"><![CDATA[Valor STAT inválido]]></phrase>
		<phrase id="CM_191"><![CDATA[Valor HEADER inválido]]></phrase>
		<phrase id="CM_192"><![CDATA[Valor DATA inválido]]></phrase>
		<phrase id="CM_193"><![CDATA[Valor ENCODE inválido]]></phrase>
		<phrase id="CM_194"><![CDATA[Cursos de treinamento]]></phrase>
		<phrase id="CM_195"><![CDATA[Funcionários com lacuna]]></phrase>
		<phrase id="CM_196"><![CDATA[Funcionários com lacunas]]></phrase>
		<phrase id="CM_197"><![CDATA[Há funcionários com lacunas para este curso]]></phrase>
		<phrase id="CM_198"><![CDATA[Atualmente não há cursos associados com a lacuna desse funcionário.]]></phrase>
		<phrase id="CM_199"><![CDATA[Não há informações para exibir sobre esse tipo de qualificação. Verifique outras guias.]]></phrase>
		<phrase id="CM_200"><![CDATA[Atualmente não há cursos associados com esta qualificação.]]></phrase>
		<phrase id="CM_201"><![CDATA[Detalhe adicional do emprego]]></phrase>
		<phrase id="CM_202"><![CDATA[Imprimindo perfil...]]></phrase>
		<phrase id="CM_203"><![CDATA[Nome do funcionário:]]></phrase>
		<phrase id="CM_204"><![CDATA[Descrição do emprego:]]></phrase>
		<phrase id="CM_205"><![CDATA[Descrição do emprego:]]></phrase>
		<phrase id="CM_206"><![CDATA[CONDIÇÕES AMBIENTAIS]]></phrase>
		<phrase id="CM_207"><![CDATA[OPERADO POR EQUIPAMENTOS]]></phrase>
		<phrase id="CM_208"><![CDATA[REQUISITOS MENTAIS]]></phrase>
		<phrase id="CM_209"><![CDATA[REQUISITOS FÍSICOS]]></phrase>
		<phrase id="CM_210"><![CDATA[SUPERVISÃO RECEBIDA]]></phrase>
		<phrase id="CM_211"><![CDATA[VIAGEM]]></phrase>
		<phrase id="CM_212"><![CDATA[Essencial]]></phrase>
		<phrase id="CM_213"><![CDATA[Porcentagem]]></phrase>
		<phrase id="CM_214"><![CDATA[Não definido]]></phrase>
		<phrase id="CM_215"><![CDATA[Selecione um de seus relatórios diretos para visualizar seu Perfil individual.]]></phrase>
		<phrase id="CM_216"><![CDATA[Para visualizar detalhes de formação, certificação e competência, ou para verificar quais cursos de treinamento estão disponíveis para as lacunas identificadas, clique na qualificação que estiver interessado.]]></phrase>
		<phrase id="CM_217"><![CDATA[Não há qualificações definidas para você ou seu emprego neste momento.]]></phrase>
		<phrase id="CM_218"><![CDATA[Não há qualificações definidas para seu emprego. Somente suas qualificações serão exibidas.]]></phrase>
		<phrase id="CM_219"><![CDATA[Não há qualificações listadas para você. Somente qualificações definidas para o emprego serão exibidas.]]></phrase>
		<phrase id="CM_220"><![CDATA[Detalhe]]></phrase>
		<phrase id="CM_221"><![CDATA[Imprimir detalhe do emprego]]></phrase>
		<phrase id="CM_222"><![CDATA[Imprimir informações detalhadas do emprego]]></phrase>
		<phrase id="CM_223"><![CDATA[Exibir descrição do emprego]]></phrase>
		<phrase id="CM_224"><![CDATA[Exibir detalhe do emprego]]></phrase>
		<phrase id="CM_225"><![CDATA[Clique para subir a página]]></phrase>
		<phrase id="CM_226"><![CDATA[Clique para descer a página]]></phrase>
		<phrase id="CM_227"><![CDATA[Qualificações]]></phrase>
		<phrase id="CM_228"><![CDATA[Qualificação adicionada.]]></phrase>
		<phrase id="CM_229"><![CDATA[Qualificação atualizada.]]></phrase>
		<phrase id="CM_230"><![CDATA[Selecione um funcionário para o qual deseja adicionar uma qualificação.]]></phrase>
		<phrase id="CM_231"><![CDATA[Detalhes de qualificação: Adicionando competência]]></phrase>
		<phrase id="CM_232"><![CDATA[Proficiência]]></phrase>
		<phrase id="CM_233"><![CDATA[Origem]]></phrase>
		<phrase id="CM_234"><![CDATA[Ciclo de renovação]]></phrase>
		<phrase id="CM_235"><![CDATA[Instrutor]]></phrase>
		<phrase id="CM_236"><![CDATA[Classificação]]></phrase>
		<phrase id="CM_237"><![CDATA[Adquirido]]></phrase>
		<phrase id="CM_238"><![CDATA[Exibir calendário]]></phrase>
		<phrase id="CM_239"><![CDATA[Usado pela última vez]]></phrase>
		<phrase id="CM_240"><![CDATA[Renovação]]></phrase>
		<phrase id="CM_241"><![CDATA[Patrocinador da empresa]]></phrase>
		<phrase id="CM_242"><![CDATA[Detalhes de qualificação: Adicionando certificação]]></phrase>
		<phrase id="CM_243"><![CDATA[Estado/Província]]></phrase>
		<phrase id="CM_244"><![CDATA[Número da licença]]></phrase>
		<phrase id="CM_245"><![CDATA[Custo]]></phrase>
		<phrase id="CM_246"><![CDATA[Moeda]]></phrase>
		<phrase id="CM_247"><![CDATA[Detalhes de qualificação: Adicionando formação]]></phrase>
		<phrase id="CM_248"><![CDATA[Nível]]></phrase>
		<phrase id="CM_249"><![CDATA[Tema]]></phrase>
		<phrase id="CM_250"><![CDATA[GPA]]></phrase>
		<phrase id="CM_251"><![CDATA[Instituição]]></phrase>
		<phrase id="CM_252"><![CDATA[Finalização]]></phrase>
		<phrase id="CM_253"><![CDATA[Em processo]]></phrase>
		<phrase id="CM_254"><![CDATA[Selecione uma qualificação.]]></phrase>
		<phrase id="CM_255"><![CDATA[Selecione um nível.]]></phrase>
		<phrase id="CM_256"><![CDATA[Selecione um assunto.]]></phrase>
		<phrase id="CM_257"><![CDATA[Para exibir os detalhes, clique na qualificação.]]></phrase>
		<phrase id="CM_258"><![CDATA[Para adicionar uma qualificação, clique no botão abaixo.]]></phrase>
		<phrase id="CM_259"><![CDATA[Adicionar qualificação]]></phrase>
		<phrase id="CM_260"><![CDATA[Exibir novo formulário de qualificação]]></phrase>
		<phrase id="CM_261"><![CDATA[Detalhes de competência]]></phrase>
		<phrase id="CM_262"><![CDATA[Excluir qualificação]]></phrase>
		<phrase id="CM_263"><![CDATA[Selecione um de seus relatórios diretos para visualizar seu detalhe de qualificação.]]></phrase>
		<phrase id="CM_264"><![CDATA[Detalhes de qualificação]]></phrase>
		<phrase id="CM_265"><![CDATA[Não há detalhes para exibir.]]></phrase>
		<phrase id="CM_266"><![CDATA[Atualizando qualificações - Aguarde.]]></phrase>
		<phrase id="CM_267"><![CDATA[2 anos]]></phrase>
		<phrase id="CM_268"><![CDATA[3 anos]]></phrase>
		<phrase id="CM_269"><![CDATA[4 anos]]></phrase>
		<phrase id="CM_270"><![CDATA[5 anos]]></phrase>
		<phrase id="CM_271"><![CDATA[6 anos]]></phrase>
		<phrase id="CM_272"><![CDATA[7 anos]]></phrase>
		<phrase id="CM_273"><![CDATA[8 anos]]></phrase>
		<phrase id="CM_274"><![CDATA[9 anos]]></phrase>
		<phrase id="CM_275"><![CDATA[Anual]]></phrase>
		<phrase id="CM_276"><![CDATA[Trimestralmente]]></phrase>
		<phrase id="CM_277"><![CDATA[Semestral]]></phrase>
		<phrase id="CM_278"><![CDATA[Sessões]]></phrase>
		<phrase id="CM_279"><![CDATA[Pré-requisitos]]></phrase>
		<phrase id="CM_280"><![CDATA[Detalhes do curso]]></phrase>
		<phrase id="CM_281"><![CDATA[Enviar inscrição]]></phrase>
		<phrase id="CM_282"><![CDATA[Selecione o funcionário que gostaria de matricular]]></phrase>
		<phrase id="CM_283"><![CDATA[Matrícula de funcionários:]]></phrase>
		<phrase id="CM_284"><![CDATA[Selecione uma sessão inscrever-se.]]></phrase>
		<phrase id="CM_285"><![CDATA[Inscrição enviada.]]></phrase>
		<phrase id="CM_286"><![CDATA[Não há sessões existentes para esse curso]]></phrase>
		<phrase id="CM_287"><![CDATA[Não há pré-requisitos definidos para o curso]]></phrase>
		<phrase id="CM_288"><![CDATA[Sessão]]></phrase>
		<phrase id="CM_289"><![CDATA[Data inicial]]></phrase>
		<phrase id="CM_290"><![CDATA[Data final]]></phrase>
		<phrase id="CM_291"><![CDATA[Local]]></phrase>
		<phrase id="CM_292"><![CDATA[Instalação]]></phrase>
		<phrase id="CM_293"><![CDATA[Tempo inicial]]></phrase>
		<phrase id="CM_294"><![CDATA[Hora final]]></phrase>
		<phrase id="CM_295"><![CDATA[Curso]]></phrase>
		<phrase id="CM_296"><![CDATA[Grupo de funcionários]]></phrase>
		<phrase id="CM_297"><![CDATA[Competência: Capacidade]]></phrase>
		<phrase id="CM_298"><![CDATA[Competência: Conhecimento]]></phrase>
		<phrase id="CM_299"><![CDATA[Competência: Outros atributos]]></phrase>
		<phrase id="CM_300"><![CDATA[Competência: Habilidade]]></phrase>
		<phrase id="CM_301"><![CDATA[Extensão do serviço]]></phrase>
		<phrase id="CM_302"><![CDATA[Dias]]></phrase>
		<phrase id="CM_303"><![CDATA[Meses]]></phrase>
		<phrase id="CM_304"><![CDATA[Anos]]></phrase>
		<phrase id="CM_305"><![CDATA[Requerido]]></phrase>
		<phrase id="CM_306"><![CDATA[Não requerido]]></phrase>
		<phrase id="CM_307"><![CDATA[Empresa]]></phrase>
		<phrase id="CM_308"><![CDATA[Data inicial]]></phrase>
		<phrase id="CM_309"><![CDATA[Qualificado]]></phrase>
		<phrase id="CM_310"><![CDATA[Mín. Proficiência]]></phrase>
		<phrase id="CM_311"><![CDATA[Tamanho]]></phrase>
		<phrase id="CM_312"><![CDATA[Selecione uma categoria antes de criar uma lista de cursos.]]></phrase>
		<phrase id="CM_313"><![CDATA[Cursos]]></phrase>
		<phrase id="CM_314"><![CDATA[Atualmente não há cursos associados com os critérios de qualificação selecionados.]]></phrase>
		<phrase id="CM_315"><![CDATA[Atualmente não há cursos oferecidos para a qualificação selecionada.]]></phrase>
		<phrase id="CM_316"><![CDATA[Atualmente não há cursos associados com essa categoria.]]></phrase>
		<phrase id="CM_317"><![CDATA[Selecione os critérios de qualificação antes de criar uma lista de cursos.]]></phrase>
		<phrase id="CM_318"><![CDATA[Não há informações para exibir sobre esse tipo de qualificação. Verifique outras guias.]]></phrase>
		<phrase id="CM_319"><![CDATA[Para lacunas de trabalho]]></phrase>
		<phrase id="CM_320"><![CDATA[Lista de lacunas]]></phrase>
		<phrase id="CM_321"><![CDATA[Selecione uma categoria de cursos abaixo para visualizar uma lista de cursos de treinamento que sua empresa oferece dentro da categoria.]]></phrase>
		<phrase id="CM_322"><![CDATA[Criar lista de cursos]]></phrase>
		<phrase id="CM_323"><![CDATA[Selecione uma qualificação abaixo para pesquisar por cursos oferecidos pela empresa. Se várias qualificações forem selecionadas, o sistema pesquisará por todos os cursos que abordam as qualificações selecionadas.]]></phrase>
		<phrase id="CM_324"><![CDATA[Para visualizar treinamentos para lacunas, é necessário selecionar um funcionário. Uma lista de lacunas será criada baseada no cargo ou emprego atual do funcionário.<p>Depois, clique em uma qualificação para visualizar quais cursos são oferecidos pela empresa.]]></phrase>
		<phrase id="CM_325"><![CDATA[Uma lista de lacunas de qualificações foi criada baseada em seu cargo ou emprego atual.<p>Clique em uma qualificação para visualizar quais cursos são oferecidos pela empresa.]]></phrase>
		<phrase id="CM_326"><![CDATA[GapDetail]]></phrase>
		<phrase id="CM_327"><![CDATA[Adicionar este anexo]]></phrase>
		<phrase id="CM_328"><![CDATA[Não há Plano de ação para exibir do funcionário selecionado.]]></phrase>
		<phrase id="CM_329"><![CDATA[Plano de ação]]></phrase>
		<phrase id="CM_330"><![CDATA[Data de revisão programada]]></phrase>
		<phrase id="CM_331"><![CDATA[Não há detalhes a serem exibidos no momento.]]></phrase>
		<phrase id="CM_332"><![CDATA[Data da retenção:]]></phrase>
		<phrase id="CM_333"><![CDATA[Classificação:]]></phrase>
		<phrase id="CM_334"><![CDATA[Revisado por:]]></phrase>
		<phrase id="CM_335"><![CDATA[Descrição do curso]]></phrase>
		<phrase id="CM_336"><![CDATA[Data de conclusão]]></phrase>
		<phrase id="CM_337"><![CDATA[Curso:]]></phrase>
		<phrase id="CM_338"><![CDATA[Status:]]></phrase>
		<phrase id="CM_339"><![CDATA[CEU concedido:]]></phrase>
		<phrase id="CM_340"><![CDATA[Notificação:]]></phrase>
		<phrase id="CM_341"><![CDATA[Data da lista de espera:]]></phrase>
		<phrase id="CM_342"><![CDATA[Data de confirmação:]]></phrase>
		<phrase id="CM_343"><![CDATA[Selecione um de seus relatórios diretos para visualizar seu Plano de ação.]]></phrase>
		<phrase id="CM_344"><![CDATA[Revisões]]></phrase>
		<phrase id="CM_345"><![CDATA[Histórico de treinamentos]]></phrase>
		<phrase id="CM_346"><![CDATA[Inscrição em treinamento]]></phrase>
		<phrase id="CM_347"><![CDATA[Detalhe adicional]]></phrase>
		<phrase id="CM_348"><![CDATA[Explorar carreiras permite a visualização de quais empregos existem em sua empresa e a comparação entre as qualificações de um funcionário com as necessárias para o emprego.<p>Selecione um cargo e um funcionário abaixo para criar um perfil de funcionário.]]></phrase>
		<phrase id="CM_349"><![CDATA[Explorar carreiras permite a visualização de quais empregos existem em sua empresa e a comparação entre as qualificações de um funcionário com as necessárias para o emprego.<p>Selecione uma categoria abaixo para visualizar os cargos associados à categoria.]]></phrase>
		<phrase id="CM_350"><![CDATA[Prosseguir]]></phrase>
		<phrase id="CM_351"><![CDATA[Para encontrar outros empregos que correspondem às qualificação de seu funcionário, selecione um funcionário e clique no botão Criar lista de empregos abaixo.]]></phrase>
		<phrase id="CM_352"><![CDATA[Visualizar Perfil de qualificação atual do funcionário]]></phrase>
		<phrase id="CM_353"><![CDATA[Se desejar adicionar outras áreas de interesse à pesquisa de empregos, selecione-as abaixo.]]></phrase>
		<phrase id="CM_354"><![CDATA[Para criar um perfil, é necessário selecionar um cargo e um funcionário.]]></phrase>
		<phrase id="CM_355"><![CDATA[Selecione um cargo.]]></phrase>
		<phrase id="CM_356"><![CDATA[Não há qualificações definidas para o funcionário ou para o emprego selecionado neste momento.]]></phrase>
		<phrase id="CM_357"><![CDATA[Não há qualificações definidas para o emprego selecionado. Somente as qualificações do funcionário selecionado serão exibidas.]]></phrase>
		<phrase id="CM_358"><![CDATA[Não há qualificações listadas para o funcionário selecionado. Somente qualificações definidas para o emprego selecionado serão exibidas.]]></phrase>
		<phrase id="CM_359"><![CDATA[Perfil de grupo]]></phrase>
		<phrase id="CM_360"><![CDATA[Selecione o funcionário e os critérios do emprego.]]></phrase>
		<phrase id="CM_361"><![CDATA[Selecione os critérios do funcionário.]]></phrase>
		<phrase id="CM_362"><![CDATA[Selecione os critérios do emprego.]]></phrase>
		<phrase id="CM_363"><![CDATA[Não há competências/qualificações definidas para este emprego.]]></phrase>
		<phrase id="CM_364"><![CDATA[Não existe lacunas de qualificação para os critérios selecionados.]]></phrase>
		<phrase id="CM_365"><![CDATA[É possível selecionar todos seus relatórios diretos, ou até 10 de forma individual. Insira seus critérios novamente.]]></phrase>
		<phrase id="CM_366"><![CDATA[Não há informações para exibir sobre esse tipo de qualificação. Verifique outras guias.]]></phrase>
		<phrase id="CM_367"><![CDATA[Para criar um perfil de grupo:]]></phrase>
		<phrase id="CM_368"><![CDATA[Selecione os funcionários que deseja incluir]]></phrase>
		<phrase id="CM_369"><![CDATA[Selecione o emprego em relação ao qual deseja compará-los]]></phrase>
		<phrase id="CM_370"><![CDATA[E clique em "Criar perfil".]]></phrase>
		<phrase id="CM_371"><![CDATA[O perfil exibe um resumo das lacunas de qualificação e identifica quais funcionários apresentam lacunas.]]></phrase>
		<phrase id="CM_372"><![CDATA[Selecionar critérios]]></phrase>
		<phrase id="CM_373"><![CDATA[Funcionários]]></phrase>
		<phrase id="CM_374"><![CDATA[Usar todos os relatórios diretos]]></phrase>
		<phrase id="CM_375"><![CDATA[ou selecionar os funcionários abaixo]]></phrase>
		<phrase id="CM_376"><![CDATA[Trabalhos]]></phrase>
		<phrase id="CM_377"><![CDATA[Usar o cargo ou emprego atual do funcionário]]></phrase>
		<phrase id="CM_378"><![CDATA[ou selecionar um cargo abaixo]]></phrase>
		<phrase id="CM_379"><![CDATA[Reiniciar]]></phrase>
		<phrase id="CM_380"><![CDATA[Redefinir formulário]]></phrase>
		<phrase id="CM_381"><![CDATA[Criar perfil de lacunas]]></phrase>
		<phrase id="CM_382"><![CDATA[Perfil individual]]></phrase>
		<phrase id="CM_383"><![CDATA[Não há qualificações definidas para o funcionário ou para o emprego selecionado neste momento.]]></phrase>
		<phrase id="CM_384"><![CDATA[Não há qualificações definidas para o emprego do funcionário. Somente as qualificações do funcionário serão exibidas.]]></phrase>
		<phrase id="CM_385"><![CDATA[Não há qualificações listadas para o funcionário. Somente qualificações definidas para o emprego do funcionário serão exibidas.]]></phrase>
		<phrase id="CM_386"><![CDATA[Plano de ação do funcionário]]></phrase>
		<phrase id="CM_387"><![CDATA[Qualificações do funcionário]]></phrase>
		<phrase id="CM_388"><![CDATA[Compare as qualificações de um funcionário com as necessárias para seu emprego. Verifique onde há lacunas.]]></phrase>
		<phrase id="CM_389"><![CDATA[Revise os objetivos do plano de ação de seu funcionário. Consulte detalhes adicionais sobre revisões e treinamento.]]></phrase>
		<phrase id="CM_390"><![CDATA[Visualize um perfil individual dos conhecimentos, habilidades, capacidades, certificações e formação de seu funcionário.]]></phrase>
		<phrase id="CM_391"><![CDATA[Verifique os empregos existentes em sua empresa. Pesquise por tipo ou por critérios de qualificação. Compare seu funcionário com o emprego.]]></phrase>
		<phrase id="CM_392"><![CDATA[Registre seus funcionários no treinamento que precisam. Pesquise por categoria ou critérios.]]></phrase>
		<phrase id="CM_393"><![CDATA[Visualize um resumo das lacunas de qualificação do emprego de seus relatórios diretos.]]></phrase>
		<phrase id="CM_394"><![CDATA[Excluir o plano de ação deste funcionário?]]></phrase>
		<phrase id="CM_395"><![CDATA[Descrição da posição:]]></phrase>
		<phrase id="CM_396"><![CDATA[Gestão de carreiras do gerente]]></phrase>
		<phrase id="CM_CLOSE"><![CDATA[Fechar]]></phrase>
		<phrase id="CM_NO_RELATED_LINK_ACCESS"><![CDATA[Você não tem acesso aos links de marcadores relacionados.]]></phrase>
		<phrase id="CM_TALENTVIEW"><![CDATA[TalentView&#174;]]></phrase>
	</Translate>
</LAWXML>
<!-- Version: 8-)@(#)@@PRODNUM@.@BUILDNUM@ -->
<!-- $Header: /cvs/cvs_archive/applications/webtier/shr/src/xhrnet/xml/lang/ptbr/Attic/cmmsgs.xml,v 1.1.4.4 2013/10/08 14:25:47 brentd Exp $ -->
<!--************************************************************
 *                                                             *
 *                           NOTICE                            *
 *                                                             *
 *   THIS SOFTWARE IS THE PROPERTY OF AND CONTAINS             *
 *   CONFIDENTIAL INFORMATION OF INFOR AND/OR ITS              *
 *   AFFILIATES OR SUBSIDIARIES AND SHALL NOT BE DISCLOSED     *
 *   WITHOUT PRIOR WRITTEN PERMISSION. LICENSED CUSTOMERS MAY  *
 *   COPY AND ADAPT THIS SOFTWARE FOR THEIR OWN USE IN         *
 *   ACCORDANCE WITH THE TERMS OF THEIR SOFTWARE LICENSE       *
 *   AGREEMENT. ALL OTHER RIGHTS RESERVED.                     *
 *                                                             *
 *   (c) COPYRIGHT 2014 INFOR.  ALL RIGHTS RESERVED.           *
 *   THE WORD AND DESIGN MARKS SET FORTH HEREIN ARE            *
 *   TRADEMARKS AND/OR REGISTERED TRADEMARKS OF INFOR          *
 *   AND/OR ITS AFFILIATES AND SUBSIDIARIES. ALL               *
 *   RIGHTS RESERVED.  ALL OTHER TRADEMARKS LISTED HEREIN ARE  *
 *   THE PROPERTY OF THEIR RESPECTIVE OWNERS.                  *
 *                                                             *
 ************************************************************--> 